django_coverage_plugin/__init__.py
django_coverage_plugin/plugin.py
django_coverage_plugin-3.1.1.dist-info/licenses/AUTHORS.txt
django_coverage_plugin-3.1.1.dist-info/licenses/LICENSE.txt
django_coverage_plugin-3.1.1.dist-info/licenses/NOTICE.txt
django_coverage_plugin-3.1.1.dist-info/METADATA
django_coverage_plugin-3.1.1.dist-info/WHEEL
django_coverage_plugin-3.1.1.dist-info/top_level.txt
django_coverage_plugin-3.1.1.dist-info/RECORD
