Metadata-Version: 2.4
Name: django_coverage_plugin
Version: 3.1.1
Summary: Django template coverage.py plugin
Author-email: Ned Batchelder <ned@nedbatchelder.com>
License-Expression: Apache-2.0
Project-URL: Homepage, https://github.com/nedbat/django_coverage_plugin
Project-URL: Bug Tracker, https://github.com/nedbat/django_coverage_plugin/issues
Project-URL: Source, https://github.com/nedbat/django_coverage_plugin
Classifier: Development Status :: 5 - Production/Stable
Classifier: Environment :: Console
Classifier: Framework :: Django
Classifier: Framework :: Django :: 2.2
Classifier: Framework :: Django :: 3.2
Classifier: Framework :: Django :: 4.2
Classifier: Framework :: Django :: 5.2
Classifier: Intended Audience :: Developers
Classifier: Operating System :: OS Independent
Classifier: Programming Language :: Python :: 3.9
Classifier: Programming Language :: Python :: 3.10
Classifier: Programming Language :: Python :: 3.11
Classifier: Programming Language :: Python :: 3.12
Classifier: Programming Language :: Python :: 3.13
Classifier: Programming Language :: Python :: Implementation :: CPython
Classifier: Programming Language :: Python :: Implementation :: PyPy
Classifier: Topic :: Software Development :: Quality Assurance
Classifier: Topic :: Software Development :: Testing
Requires-Python: >=3.9
License-File: LICENSE.txt
License-File: NOTICE.txt
License-File: AUTHORS.txt
Requires-Dist: coverage
Dynamic: license-file
